example_app/__init__.py
example_app/settings.py
example_app/urls.py
example_app/wsgi.py
youtube_django/__init__.py
youtube_django/admin.py
youtube_django/apps.py
youtube_django/models.py
youtube_django/tests.py
youtube_django/urls.py
youtube_django/views.py
youtube_django/migrations/0001_initial.py
youtube_django/migrations/__init__.py
youtube_django-0.2.1.dist-info/METADATA
youtube_django-0.2.1.dist-info/RECORD
youtube_django-0.2.1.dist-info/WHEEL
youtube_django-0.2.1.dist-info/top_level.txt
